mcp_timeserver/__init__.py
mcp_timeserver/server.py
mcp_timeserver_fastmcp-0.1.1.dist-info/METADATA
mcp_timeserver_fastmcp-0.1.1.dist-info/WHEEL
mcp_timeserver_fastmcp-0.1.1.dist-info/entry_points.txt
mcp_timeserver_fastmcp-0.1.1.dist-info/licenses/LICENSE
mcp_timeserver_fastmcp-0.1.1.dist-info/RECORD
