Metadata-Version: 2.4
Name: mcp-timeserver-fastmcp
Version: 0.1.1
Summary: An MCP server for providing the current date/time to LLMs
Project-URL: Homepage, https://github.com/fastmcp-me/mcp-timeserver#readme
Project-URL: Repository, https://github.com/fastmcp-me/mcp-timeserver.git
Project-URL: Issues, https://github.com/fastmcp-me/mcp-timeserver/issues
Author-email: TerminalMan <84923604+SecretiveShell@users.noreply.github.com>
License-File: LICENSE
Requires-Python: >=3.12
Requires-Dist: mcp>=1.1.2
Requires-Dist: tzdata>=2024.2
